pysphalt/__init__.py
pysphalt/models.py
pysphalt/schemas.py
pysphalt/pickle_models/asphalt_modulus_predictor.pkl
pysphalt-0.1.21.dist-info/LICENSE
pysphalt-0.1.21.dist-info/METADATA
pysphalt-0.1.21.dist-info/WHEEL
pysphalt-0.1.21.dist-info/top_level.txt
pysphalt-0.1.21.dist-info/RECORD
