Metadata-Version: 2.1
Name: pysphalt
Version: 0.1.21
Summary: Library of Descriptive and Predictive Models for Brazilian Asphalt Materials Data
Home-page: https://pysphalt.readthedocs.io
Author: Rodrigo Castanon
Author-email: Rodrigo Castanon <rodrigo.castanon@poli.ufrj.br>
License: MIT License
Project-URL: Homepage, https://pysphalt.readthedocs.io
Project-URL: Documentation, https://pysphalt.readthedocs.io
Project-URL: Repository, https://github.com/pysphalt/pysphalt
Project-URL: Issues, https://github.com/pysphalt/pysphalt/issues
Classifier: Intended Audience :: Developers
Classifier: Programming Language :: Python :: 3
Classifier: License :: OSI Approved :: MIT License
Classifier: Operating System :: OS Independent
Requires-Python: >=3.10
License-File: LICENSE
